LICENSE.txt
README.rst
setup.py
skysenseremote/__init__.py
skysenseremote/build.py
skysenseremote.egg-info/PKG-INFO
skysenseremote.egg-info/SOURCES.txt
skysenseremote.egg-info/dependency_links.txt
skysenseremote.egg-info/requires.txt
skysenseremote.egg-info/top_level.txt
skysenseremote/configs/__init__.py
skysenseremote/configs/args.py
skysenseremote/configs/args1024.py
skysenseremote/dataset/__init__.py
skysenseremote/dataset/dataset.py
skysenseremote/dataset/dataset0.py
skysenseremote/model/__init__.py
skysenseremote/model/net.py
skysenseremote/model/backbone/__init__.py
skysenseremote/model/backbone/checkpoint.py
skysenseremote/model/backbone/swin4skysense.py
skysenseremote/model/semseg/GCM.py
skysenseremote/model/semseg/__init__.py
skysenseremote/model/semseg/base.py
skysenseremote/model/semseg/upernet.py
skysenseremote/model/semseg/lib_upernet/__init__.py
skysenseremote/model/semseg/lib_upernet/nn/__init__.py
skysenseremote/model/semseg/lib_upernet/nn/modules/__init__.py
skysenseremote/model/semseg/lib_upernet/nn/modules/batchnorm.py
skysenseremote/model/semseg/lib_upernet/nn/modules/comm.py
skysenseremote/model/semseg/lib_upernet/nn/modules/replicate.py
skysenseremote/model/semseg/lib_upernet/nn/modules/unittest.py
skysenseremote/model/semseg/lib_upernet/nn/parallel/__init__.py
skysenseremote/model/semseg/lib_upernet/nn/parallel/data_parallel.py
skysenseremote/model/semseg/lib_upernet/nn/prroi_pool/__init__.py
skysenseremote/model/semseg/lib_upernet/nn/prroi_pool/functional.py
skysenseremote/model/semseg/lib_upernet/nn/prroi_pool/prroi_pool.py
skysenseremote/model/semseg/lib_upernet/nn/prroi_pool/test_prroi_pooling2d.py
skysenseremote/utils/__init__.py
skysenseremote/utils/metrics.py
skysenseremote/utils/net_utils.py
skysenseremote/utils/path.py